moa_llm/__init__.py
moa_llm/aggregation_layer.py
moa_llm/config_loader.py
moa_llm/layer.py
moa_llm/mixture_of_agents.py
moa_llm/neuron.py
moa_llm/user_query_annotator.py
moa_llm/version.py
moa_llm-0.1.0.dist-info/LICENSE
moa_llm-0.1.0.dist-info/METADATA
moa_llm-0.1.0.dist-info/WHEEL
moa_llm-0.1.0.dist-info/top_level.txt
moa_llm-0.1.0.dist-info/RECORD
