Metadata-Version: 2.1
Name: moa-llm
Version: 0.1.0
Author-email: Joao Fiadeiro <joao@catena.xyz>, Anjor Kanekar <anjor@catena.xyz>
License: MIT License
Project-URL: Homepage, https://github.com/catena-labs/moa-llm
Project-URL: Repository, https://github.com/catena-labs/moa-llm
Classifier: Topic :: Scientific/Engineering :: Artificial Intelligence
Requires-Python: >=3.8
License-File: LICENSE
Requires-Dist: openai
Requires-Dist: python-dotenv
Requires-Dist: PyYAML
Provides-Extra: dev
Requires-Dist: ruff; extra == "dev"
Requires-Dist: black<24.0,>=23.0; extra == "dev"
Requires-Dist: isort<5.14,>=5.12; extra == "dev"
Requires-Dist: pytest; extra == "dev"
Requires-Dist: pytest-sphinx; extra == "dev"
Requires-Dist: pytest-cov; extra == "dev"
Requires-Dist: twine>=1.11.0; extra == "dev"
Requires-Dist: build; extra == "dev"
Requires-Dist: setuptools; extra == "dev"
Requires-Dist: wheel; extra == "dev"
Requires-Dist: packaging; extra == "dev"
